docs/API_reference.rst
docs/Makefile
docs/authors.rst
docs/conf.py
docs/contributing.rst
docs/guide.rst
docs/index.rst
docs/installation.rst
docs/make.bat
docs/images/.gitkeep
docs/images/Bezier1.png
docs/images/Bezier2.png
docs/images/Bezier3.png
docs/images/creep.png
docs/images/decos.png
docs/images/di.png
docs/images/hp.png
docs/images/interpolate.png
docs/images/singrid.png
docs/images/uf.png
docs/images/ui.png
examples/20141003_24.h5
examples/F20190424_1.h5
examples/pyfastspm_converter.ipynb
pyfastspm/__init__.py
pyfastspm/_version.py
pyfastspm/fast_movie.py
pyfastspm/artefact_removal/__init__.py
pyfastspm/artefact_removal/creep.py
pyfastspm/artefact_removal/drift.py
pyfastspm/artefact_removal/fft.py
pyfastspm/artefact_removal/filters.py
pyfastspm/artefact_removal/image_correction.py
pyfastspm/artefact_removal/interpolate.py
pyfastspm/tools/__init__.py
pyfastspm/tools/decorators.py
pyfastspm/tools/error_catcher.py
pyfastspm/tools/exporter.py
pyfastspm/tools/file_handling_tools.py
pyfastspm/tools/frame_artists.py
pyfastspm/tools/resources/__init__.py
pyfastspm/tools/resources/fonts/OpenSans-Semibold.ttf
pyfastspm/tools/resources/fonts/__init__.py
pyfastspm/tracking/__init__.py
pyfastspm/tracking/pixel_trace.py
pyfastspm-1.0.6.dist-info/licenses/AUTHORS.rst
pyfastspm-1.0.6.dist-info/licenses/LICENSE
pyfastspm-1.0.6.dist-info/METADATA
pyfastspm-1.0.6.dist-info/WHEEL
pyfastspm-1.0.6.dist-info/top_level.txt
pyfastspm-1.0.6.dist-info/RECORD
