Metadata-Version: 2.4
Name: pyfastspm
Version: 1.0.6
Summary: A python package for loading, processing and exporting scanning probe microscopy movies acquired with the FAST unit.
Author-email: Carlo Dri <carlo.dri@gmail.com>
License: MIT
Project-URL: Homepage, https://gitlab.com/fastspm/pyfastspm
Project-URL: Issues, https://gitlab.com/fastspm/pyfastspm/-/issues
Classifier: Programming Language :: Python :: 3.6
Classifier: Programming Language :: Python :: 3.7
Classifier: Programming Language :: Python :: 3.8
Classifier: Programming Language :: Python :: 3.9
Classifier: Programming Language :: Python :: 3.10
Classifier: Programming Language :: Python :: 3.11
Classifier: Programming Language :: Python :: 3.12
Classifier: License :: OSI Approved :: MIT License
Classifier: License :: OSI Approved :: Apache Software License
Classifier: Operating System :: OS Independent
Classifier: Development Status :: 4 - Beta
Classifier: Intended Audience :: Science/Research
Classifier: Natural Language :: English
Requires-Python: >=3.6
License-File: LICENSE
License-File: AUTHORS.rst
Requires-Dist: h5py
Requires-Dist: matplotlib
Requires-Dist: numpy
Requires-Dist: packaging
Requires-Dist: pillow
Requires-Dist: scikit-image
Requires-Dist: scipy
Requires-Dist: setuptools-scm
Requires-Dist: tqdm
Provides-Extra: mkl-fft
Requires-Dist: mkl_fft; extra == "mkl-fft"
Dynamic: license-file
